odoo/addons/purchase_advance_payment/README.rst
odoo/addons/purchase_advance_payment/__init__.py
odoo/addons/purchase_advance_payment/__manifest__.py
odoo/addons/purchase_advance_payment/i18n/es.po
odoo/addons/purchase_advance_payment/i18n/fr.po
odoo/addons/purchase_advance_payment/i18n/it.po
odoo/addons/purchase_advance_payment/i18n/pt_BR.po
odoo/addons/purchase_advance_payment/i18n/purchase_advance_payment.pot
odoo/addons/purchase_advance_payment/models/__init__.py
odoo/addons/purchase_advance_payment/models/payment.py
odoo/addons/purchase_advance_payment/models/purchase_order.py
odoo/addons/purchase_advance_payment/readme/CONTRIBUTORS.rst
odoo/addons/purchase_advance_payment/readme/DESCRIPTION.rst
odoo/addons/purchase_advance_payment/readme/USAGE.rst
odoo/addons/purchase_advance_payment/security/ir.model.access.csv
odoo/addons/purchase_advance_payment/static/description/icon.png
odoo/addons/purchase_advance_payment/static/description/index.html
odoo/addons/purchase_advance_payment/tests/__init__.py
odoo/addons/purchase_advance_payment/tests/test_purchase_advance_payment.py
odoo/addons/purchase_advance_payment/views/purchase_view.xml
odoo/addons/purchase_advance_payment/wizard/__init__.py
odoo/addons/purchase_advance_payment/wizard/purchase_advance_payment_wizard.py
odoo/addons/purchase_advance_payment/wizard/purchase_advance_payment_wizard_view.xml
odoo14_addon_purchase_advance_payment-14.0.1.1.3.dist-info/METADATA
odoo14_addon_purchase_advance_payment-14.0.1.1.3.dist-info/WHEEL
odoo14_addon_purchase_advance_payment-14.0.1.1.3.dist-info/top_level.txt
odoo14_addon_purchase_advance_payment-14.0.1.1.3.dist-info/RECORD
