Metadata-Version: 2.1
Name: odoo14-addon-purchase_advance_payment
Version: 14.0.1.1.3
Summary: Allow to add advance payments on purchase orders
Home-page: https://github.com/OCA/purchase-workflow
Author: Forgeflow, Odoo Community Association (OCA)
Author-email: support@odoo-community.org
License: AGPL-3
Classifier: Programming Language :: Python
Classifier: Framework :: Odoo
Classifier: Framework :: Odoo :: 14.0
Classifier: License :: OSI Approved :: GNU Affero General Public License v3
Requires-Python: >=3.6
Requires-Dist: odoo<14.1dev,>=14.0a
